MSATwtdenoiser/MSATwtdenoiser.py
MSATwtdenoiser/__init__.py
MSATwtdenoiser/example.py
MSATwtdenoiser/example_xch4.py
MSATwtdenoiser-0.0.6.dist-info/LICENSE
MSATwtdenoiser-0.0.6.dist-info/METADATA
MSATwtdenoiser-0.0.6.dist-info/WHEEL
MSATwtdenoiser-0.0.6.dist-info/top_level.txt
MSATwtdenoiser-0.0.6.dist-info/RECORD
