Metadata-Version: 2.1
Name: MSATwtdenoiser
Version: 0.0.6
Summary: Denoising a 2D signal based on wavelet
Home-page: https://github.com/ahsouri/MSATwtdenoiser
Author: Amir Souri
Author-email: ahsouri@gmail.com
License: MIT
Platform: UNKNOWN
License-File: LICENSE
Requires-Dist: numpy
Requires-Dist: matplotlib
Requires-Dist: scipy
Requires-Dist: PyWavelets
Requires-Dist: opencv-python
